igp_plotter/__init__.py
igp_plotter/core.py
igp_plotter/decoder.py
igp_plotter/grid.py
igp_plotter/plotter.py
igp_plotter/processor.py
igp_plotter-0.1.0.dist-info/licenses/LICENSE
igp_plotter-0.1.0.dist-info/METADATA
igp_plotter-0.1.0.dist-info/WHEEL
igp_plotter-0.1.0.dist-info/top_level.txt
igp_plotter-0.1.0.dist-info/RECORD
