Metadata-Version: 2.4
Name: igp-plotter
Version: 0.1.0
Summary: Python library for decoding and visualizing SBAS IGP grid coverage
Author-email: Yash Patel <yash.patel@example.com>
License: MIT
Classifier: Programming Language :: Python :: 3
Classifier: License :: OSI Approved :: MIT License
Classifier: Operating System :: OS Independent
Requires-Python: >=3.9
License-File: LICENSE
Requires-Dist: pandas
Requires-Dist: matplotlib
Requires-Dist: geopandas
Requires-Dist: shapely
Requires-Dist: geodatasets
Dynamic: license-file
